memdem
