Metadata-Version: 2.1
Name: memdem
Version: 0.1.0.post1
Summary: Make use of open global elevation data from [Terrain Tiles](https://registry.opendata.aws/terrain-tiles) to create digital elevation models (DEM) on the fly.
Home-page: https://github.com/underchemist/memdem
Author: Yann-Sebastien Tremblay-Johnston
Author-email: yanns.tremblay@gmail.com
License: MIT
Project-URL: Issues, https://github.com/underchemist/memdem/Issues
Project-URL: Changelog, https://github.com/underchemist/memdem/blob/master/CHANGELOG.md
Keywords: geospatial,gis
Platform: any
Classifier: Development Status :: 3 - Alpha
Classifier: Intended Audience :: Developers
Classifier: Intended Audience :: Science/Research
Classifier: Topic :: Scientific/Engineering :: GIS
Classifier: Topic :: Software Development :: Libraries
Classifier: License :: OSI Approved :: MIT License
Classifier: Operating System :: OS Independent
Classifier: Programming Language :: Python
Classifier: Programming Language :: Python :: 3.6
Classifier: Programming Language :: Python :: 3.7
Classifier: Programming Language :: Python :: 3.8
Classifier: Programming Language :: Python :: 3.9
Requires-Python: >=3.6
Provides-Extra: dev
